{
	"jobs" : [
		{
			"type" : "load",
			"config" : { // the place to override the default configuration for this load job
				"item" : {
					"container" : {
						"name" : "bucketObjects100KB"
					},
					"data" : {
						"size" : "100KB"
					},
					"dst" : {
						"file" : "/tmp/write100KB.csv"
					}
				},
				"load" : {
					"class" : "write",
					"threads" : 100,
					"limit" : {
						"count" : 1000
					}
				}
			}
		},
		{
			"type" : "parallel",
			"jobs" : [
				{
					"type" : "load",
					"config" : {
						"item" : {
							"container" : {
								"name" : "bucketObjects100MB"
							},
							"data" : {
								"size" : "100MB"
							},
							"dst" : {
								"file" : "/tmp/write100MB.csv"
							}
						},
						"load" : {
							"class" : "write",
							"threads" : 10,
							"limit" : {
								"rate" : 1000,
								"time" : "1m"
							}
						}
					}
				},
				{
					"type" : "load",
					"config" : {
						"item" : {
							"container" : {
								"name" : "bucketObjects100KB"
							},
							"src" : {
								"file" : "/tmp/write100KB.csv"
							}
						},
						"load" : {
							"class" : "read",
							"circular" : true,
							"threads" : 10,
							"limit" : {
								"time" : "1m"
							}
						}
					}
				}
			]
		},
		{
			"type" : "sequential",
			"jobs" : [
				{
					"type" : "parallel",
					"jobs" : [
						{
							"type" : "load",
							"config" : {
								"item" : {
									"data" : {
										"size" : "16KB"
									}
								},
								"load" : {
									"class" : "write",
									"threads" : 200,
									"limit" : {
										"time" : "30s"
									}
								}
							}
						},
						{
							"type" : "load",
							"config" : {
								"item" : {
									"container" : {
										"name" : "bucketObjects100MB"
									},
									"data" : {
										"content" : {
											"verify" : false
										}
									},
									"src" : {
										"file" : "/tmp/write100MB.csv"
									}
								},
								"load" : {
									"class" : "read",
									"threads" : 100
								}
							}
						}
					]
				},
				{
					"type" : "load" // use the default configuration for this load job
				}
			]
		}
	]
}
