{
	"type" : "sequential",
	"jobs" : [
		{
			"type" : "precondition",
			"config" : {
				"item" : {
					"output" : {
						"file" : "items2read.csv",
						"path" : "items2read"
					}
				}
			}
		},
		{
			"type" : "mixed",
			"config" : [
				{
					"item" : {
						"output" : {
							"path" : "default"
						}
					},
					"storage" : {
						"driver" : {
							"concurrency" : 20
						}
					},
					"test" : {
						"step" : {
							"limit" : {
								"count" : 0
							}
						}
					}
				},
				{
					"item" : {
						"data" : {
							"verify" : true
						},
						"input" : {
							"file" : "items2read.csv"
						},
						"output" : {
							"path" : "items2read"
						}
					},
					"storage" : {
						"driver" : {
							"concurrency" : 50
						}
					},
					"test" : {
						"step" : {
							"limit" : {
								"count" : 0
							}
						}
					},
					"load" : {
						"circular" : true,
						"type" : "read"
					}
				}
			]
		}
	]
}
